{
    "uuid": "f407f26b-2d3c-4de5-b7fb-71c9eeaaf261",
    "shortName": "Transit",
    "longName": "Transit Watch",
    "companyName": "Cryptr",
    "versionCode": 1,
    "versionLabel": "1.0.0",
    "watchapp": {
        "watchface": false
    },
    "appKeys": {
        "dummy": 0
    },
    "resources": {
        "media": [
            {
                "type": "png-trans",
                "name": "IMAGE_LOGO",
                "file": "images/pebble-app-icon-large.png"
            },
            {
                "menuIcon": true,
                "type": "png",
                "name": "IMAGE_MENU_ICON",
                "file": "images/pebble-menu-image.png"
            }
        ]
    }
}
